ad_user_manager/__init__.py
ad_user_manager/__main__.py
ad_user_manager/cli.py
ad_user_manager/config.py
ad_user_manager/exceptions.py
ad_user_manager/factory.py
ad_user_manager/ldap_manager.py
ad_user_manager/models.py
ad_user_manager/powershell_manager.py
ad_user_manager/utils.py
ad_user_manager/validators.py
ad_user_manager-1.0.0.dist-info/METADATA
ad_user_manager-1.0.0.dist-info/WHEEL
ad_user_manager-1.0.0.dist-info/entry_points.txt
ad_user_manager-1.0.0.dist-info/RECORD
