Metadata-Version: 2.4
Name: ad-user-manager
Version: 1.0.0
Summary: Modern Active Directory user management tool with conflict resolution
Requires-Python: >=3.12
Requires-Dist: click>=8.2.1
Requires-Dist: ldap3>=2.9.1
Requires-Dist: pydantic-settings>=2.10.1
Requires-Dist: pydantic>=2.11.7
Requires-Dist: rich>=14.0.0
Requires-Dist: structlog>=25.4.0
Provides-Extra: dev
Requires-Dist: black>=24.0.0; extra == 'dev'
Requires-Dist: mypy>=1.8.0; extra == 'dev'
Requires-Dist: pytest-cov>=4.0.0; extra == 'dev'
Requires-Dist: pytest-mock>=3.10.0; extra == 'dev'
Requires-Dist: pytest>=8.0.0; extra == 'dev'
Requires-Dist: ruff>=0.1.0; extra == 'dev'
